pyroll/wusatowski_spreading.py
pyroll_wusatowski_spreading-3.0.0.dist-info/METADATA
pyroll_wusatowski_spreading-3.0.0.dist-info/WHEEL
pyroll_wusatowski_spreading-3.0.0.dist-info/licenses/LICENSE
pyroll_wusatowski_spreading-3.0.0.dist-info/RECORD
